{"nodes": [{"id": "c_users_jitendra_pandit_downloads_adapttutor_adapttutor_watcher_py", "label": "watcher.py", "file_type": "code", "source_file": "C:\\Users\\Jitendra Pandit\\Downloads\\AdaptTutor\\adapttutor\\watcher.py", "source_location": "L1"}, {"id": "watcher_safe_get_active_window_title", "label": "_safe_get_active_window_title()", "file_type": "code", "source_file": "C:\\Users\\Jitendra Pandit\\Downloads\\AdaptTutor\\adapttutor\\watcher.py", "source_location": "L13"}, {"id": "watcher_title_has_study_keyword", "label": "_title_has_study_keyword()", "file_type": "code", "source_file": "C:\\Users\\Jitendra Pandit\\Downloads\\AdaptTutor\\adapttutor\\watcher.py", "source_location": "L22"}, {"id": "watcher_title_has_native_study_suffix", "label": "_title_has_native_study_suffix()", "file_type": "code", "source_file": "C:\\Users\\Jitendra Pandit\\Downloads\\AdaptTutor\\adapttutor\\watcher.py", "source_location": "L30"}, {"id": "watcher_is_study_title", "label": "_is_study_title()", "file_type": "code", "source_file": "C:\\Users\\Jitendra Pandit\\Downloads\\AdaptTutor\\adapttutor\\watcher.py", "source_location": "L41"}, {"id": "watcher_extract_page_number", "label": "_extract_page_number()", "file_type": "code", "source_file": "C:\\Users\\Jitendra Pandit\\Downloads\\AdaptTutor\\adapttutor\\watcher.py", "source_location": "L53"}, {"id": "watcher_watcherstate", "label": "WatcherState", "file_type": "code", "source_file": "C:\\Users\\Jitendra Pandit\\Downloads\\AdaptTutor\\adapttutor\\watcher.py", "source_location": "L68"}, {"id": "watcher_windowwatcher", "label": "WindowWatcher", "file_type": "code", "source_file": "C:\\Users\\Jitendra Pandit\\Downloads\\AdaptTutor\\adapttutor\\watcher.py", "source_location": "L74"}, {"id": "watcher_windowwatcher_init", "label": ".__init__()", "file_type": "code", "source_file": "C:\\Users\\Jitendra Pandit\\Downloads\\AdaptTutor\\adapttutor\\watcher.py", "source_location": "L75"}, {"id": "watcher_windowwatcher_stop", "label": ".stop()", "file_type": "code", "source_file": "C:\\Users\\Jitendra Pandit\\Downloads\\AdaptTutor\\adapttutor\\watcher.py", "source_location": "L98"}, {"id": "watcher_windowwatcher_get_state", "label": ".get_state()", "file_type": "code", "source_file": "C:\\Users\\Jitendra Pandit\\Downloads\\AdaptTutor\\adapttutor\\watcher.py", "source_location": "L101"}, {"id": "watcher_windowwatcher_run", "label": ".run()", "file_type": "code", "source_file": "C:\\Users\\Jitendra Pandit\\Downloads\\AdaptTutor\\adapttutor\\watcher.py", "source_location": "L105"}, {"id": "watcher_rationale_23", "label": "Substring match on extensions / terms (browsers and generic study strings).", "file_type": "rationale", "source_file": "C:\\Users\\Jitendra Pandit\\Downloads\\AdaptTutor\\adapttutor\\watcher.py", "source_location": "L23"}, {"id": "watcher_rationale_31", "label": "Native apps: e.g. 'Document1.docx - Word', 'Chapter3.pdf - Adobe Acrobat'.     M", "file_type": "rationale", "source_file": "C:\\Users\\Jitendra Pandit\\Downloads\\AdaptTutor\\adapttutor\\watcher.py", "source_location": "L31"}], "edges": [{"source": "c_users_jitendra_pandit_downloads_adapttutor_adapttutor_watcher_py", "target": "re", "relation": "imports", "confidence": "EXTRACTED", "source_file": "C:\\Users\\Jitendra Pandit\\Downloads\\AdaptTutor\\adapttutor\\watcher.py", "source_location": "L3", "weight": 1.0}, {"source": "c_users_jitendra_pandit_downloads_adapttutor_adapttutor_watcher_py", "target": "threading", "relation": "imports", "confidence": "EXTRACTED", "source_file": "C:\\Users\\Jitendra Pandit\\Downloads\\AdaptTutor\\adapttutor\\watcher.py", "source_location": "L4", "weight": 1.0}, {"source": "c_users_jitendra_pandit_downloads_adapttutor_adapttutor_watcher_py", "target": "dataclasses", "relation": "imports_from", "confidence": "EXTRACTED", "source_file": "C:\\Users\\Jitendra Pandit\\Downloads\\AdaptTutor\\adapttutor\\watcher.py", "source_location": "L5", "weight": 1.0}, {"source": "c_users_jitendra_pandit_downloads_adapttutor_adapttutor_watcher_py", "target": "typing", "relation": "imports_from", "confidence": "EXTRACTED", "source_file": "C:\\Users\\Jitendra Pandit\\Downloads\\AdaptTutor\\adapttutor\\watcher.py", "source_location": "L6", "weight": 1.0}, {"source": "c_users_jitendra_pandit_downloads_adapttutor_adapttutor_watcher_py", "target": "pygetwindow", "relation": "imports", "confidence": "EXTRACTED", "source_file": "C:\\Users\\Jitendra Pandit\\Downloads\\AdaptTutor\\adapttutor\\watcher.py", "source_location": "L8", "weight": 1.0}, {"source": "c_users_jitendra_pandit_downloads_adapttutor_adapttutor_watcher_py", "target": "c_users_jitendra_pandit_downloads_adapttutor_adapttutor_config_py", "relation": "imports_from", "confidence": "EXTRACTED", "source_file": "C:\\Users\\Jitendra Pandit\\Downloads\\AdaptTutor\\adapttutor\\watcher.py", "source_location": "L10", "weight": 1.0}, {"source": "c_users_jitendra_pandit_downloads_adapttutor_adapttutor_watcher_py", "target": "watcher_safe_get_active_window_title", "relation": "contains", "confidence": "EXTRACTED", "source_file": "C:\\Users\\Jitendra Pandit\\Downloads\\AdaptTutor\\adapttutor\\watcher.py", "source_location": "L13", "weight": 1.0}, {"source": "c_users_jitendra_pandit_downloads_adapttutor_adapttutor_watcher_py", "target": "watcher_title_has_study_keyword", "relation": "contains", "confidence": "EXTRACTED", "source_file": "C:\\Users\\Jitendra Pandit\\Downloads\\AdaptTutor\\adapttutor\\watcher.py", "source_location": "L22", "weight": 1.0}, {"source": "c_users_jitendra_pandit_downloads_adapttutor_adapttutor_watcher_py", "target": "watcher_title_has_native_study_suffix", "relation": "contains", "confidence": "EXTRACTED", "source_file": "C:\\Users\\Jitendra Pandit\\Downloads\\AdaptTutor\\adapttutor\\watcher.py", "source_location": "L30", "weight": 1.0}, {"source": "c_users_jitendra_pandit_downloads_adapttutor_adapttutor_watcher_py", "target": "watcher_is_study_title", "relation": "contains", "confidence": "EXTRACTED", "source_file": "C:\\Users\\Jitendra Pandit\\Downloads\\AdaptTutor\\adapttutor\\watcher.py", "source_location": "L41", "weight": 1.0}, {"source": "c_users_jitendra_pandit_downloads_adapttutor_adapttutor_watcher_py", "target": "watcher_extract_page_number", "relation": "contains", "confidence": "EXTRACTED", "source_file": "C:\\Users\\Jitendra Pandit\\Downloads\\AdaptTutor\\adapttutor\\watcher.py", "source_location": "L53", "weight": 1.0}, {"source": "c_users_jitendra_pandit_downloads_adapttutor_adapttutor_watcher_py", "target": "watcher_watcherstate", "relation": "contains", "confidence": "EXTRACTED", "source_file": "C:\\Users\\Jitendra Pandit\\Downloads\\AdaptTutor\\adapttutor\\watcher.py", "source_location": "L68", "weight": 1.0}, {"source": "c_users_jitendra_pandit_downloads_adapttutor_adapttutor_watcher_py", "target": "watcher_windowwatcher", "relation": "contains", "confidence": "EXTRACTED", "source_file": "C:\\Users\\Jitendra Pandit\\Downloads\\AdaptTutor\\adapttutor\\watcher.py", "source_location": "L74", "weight": 1.0}, {"source": "watcher_windowwatcher", "target": "watcher_windowwatcher_init", "relation": "method", "confidence": "EXTRACTED", "source_file": "C:\\Users\\Jitendra Pandit\\Downloads\\AdaptTutor\\adapttutor\\watcher.py", "source_location": "L75", "weight": 1.0}, {"source": "watcher_windowwatcher", "target": "watcher_windowwatcher_stop", "relation": "method", "confidence": "EXTRACTED", "source_file": "C:\\Users\\Jitendra Pandit\\Downloads\\AdaptTutor\\adapttutor\\watcher.py", "source_location": "L98", "weight": 1.0}, {"source": "watcher_windowwatcher", "target": "watcher_windowwatcher_get_state", "relation": "method", "confidence": "EXTRACTED", "source_file": "C:\\Users\\Jitendra Pandit\\Downloads\\AdaptTutor\\adapttutor\\watcher.py", "source_location": "L101", "weight": 1.0}, {"source": "watcher_windowwatcher", "target": "watcher_windowwatcher_run", "relation": "method", "confidence": "EXTRACTED", "source_file": "C:\\Users\\Jitendra Pandit\\Downloads\\AdaptTutor\\adapttutor\\watcher.py", "source_location": "L105", "weight": 1.0}, {"source": "watcher_is_study_title", "target": "watcher_title_has_study_keyword", "relation": "calls", "confidence": "EXTRACTED", "source_file": "C:\\Users\\Jitendra Pandit\\Downloads\\AdaptTutor\\adapttutor\\watcher.py", "source_location": "L44", "weight": 1.0}, {"source": "watcher_is_study_title", "target": "watcher_title_has_native_study_suffix", "relation": "calls", "confidence": "EXTRACTED", "source_file": "C:\\Users\\Jitendra Pandit\\Downloads\\AdaptTutor\\adapttutor\\watcher.py", "source_location": "L44", "weight": 1.0}, {"source": "watcher_windowwatcher_init", "target": "watcher_watcherstate", "relation": "calls", "confidence": "EXTRACTED", "source_file": "C:\\Users\\Jitendra Pandit\\Downloads\\AdaptTutor\\adapttutor\\watcher.py", "source_location": "L96", "weight": 1.0}, {"source": "watcher_windowwatcher_run", "target": "watcher_safe_get_active_window_title", "relation": "calls", "confidence": "EXTRACTED", "source_file": "C:\\Users\\Jitendra Pandit\\Downloads\\AdaptTutor\\adapttutor\\watcher.py", "source_location": "L111", "weight": 1.0}, {"source": "watcher_windowwatcher_run", "target": "watcher_is_study_title", "relation": "calls", "confidence": "EXTRACTED", "source_file": "C:\\Users\\Jitendra Pandit\\Downloads\\AdaptTutor\\adapttutor\\watcher.py", "source_location": "L113", "weight": 1.0}, {"source": "watcher_windowwatcher_run", "target": "watcher_extract_page_number", "relation": "calls", "confidence": "EXTRACTED", "source_file": "C:\\Users\\Jitendra Pandit\\Downloads\\AdaptTutor\\adapttutor\\watcher.py", "source_location": "L114", "weight": 1.0}, {"source": "watcher_windowwatcher_run", "target": "watcher_watcherstate", "relation": "calls", "confidence": "EXTRACTED", "source_file": "C:\\Users\\Jitendra Pandit\\Downloads\\AdaptTutor\\adapttutor\\watcher.py", "source_location": "L117", "weight": 1.0}, {"source": "watcher_rationale_23", "target": "watcher_title_has_study_keyword", "relation": "rationale_for", "confidence": "EXTRACTED", "source_file": "C:\\Users\\Jitendra Pandit\\Downloads\\AdaptTutor\\adapttutor\\watcher.py", "source_location": "L23", "weight": 1.0}, {"source": "watcher_rationale_31", "target": "watcher_title_has_native_study_suffix", "relation": "rationale_for", "confidence": "EXTRACTED", "source_file": "C:\\Users\\Jitendra Pandit\\Downloads\\AdaptTutor\\adapttutor\\watcher.py", "source_location": "L31", "weight": 1.0}], "raw_calls": [{"caller_nid": "watcher_safe_get_active_window_title", "callee": "getActiveWindow", "source_file": "C:\\Users\\Jitendra Pandit\\Downloads\\AdaptTutor\\adapttutor\\watcher.py", "source_location": "L15"}, {"caller_nid": "watcher_safe_get_active_window_title", "callee": "getattr", "source_file": "C:\\Users\\Jitendra Pandit\\Downloads\\AdaptTutor\\adapttutor\\watcher.py", "source_location": "L16"}, {"caller_nid": "watcher_title_has_study_keyword", "callee": "lower", "source_file": "C:\\Users\\Jitendra Pandit\\Downloads\\AdaptTutor\\adapttutor\\watcher.py", "source_location": "L24"}, {"caller_nid": "watcher_title_has_study_keyword", "callee": "any", "source_file": "C:\\Users\\Jitendra Pandit\\Downloads\\AdaptTutor\\adapttutor\\watcher.py", "source_location": "L27"}, {"caller_nid": "watcher_title_has_native_study_suffix", "callee": "lower", "source_file": "C:\\Users\\Jitendra Pandit\\Downloads\\AdaptTutor\\adapttutor\\watcher.py", "source_location": "L35"}, {"caller_nid": "watcher_title_has_native_study_suffix", "callee": "strip", "source_file": "C:\\Users\\Jitendra Pandit\\Downloads\\AdaptTutor\\adapttutor\\watcher.py", "source_location": "L35"}, {"caller_nid": "watcher_title_has_native_study_suffix", "callee": "any", "source_file": "C:\\Users\\Jitendra Pandit\\Downloads\\AdaptTutor\\adapttutor\\watcher.py", "source_location": "L38"}, {"caller_nid": "watcher_title_has_native_study_suffix", "callee": "endswith", "source_file": "C:\\Users\\Jitendra Pandit\\Downloads\\AdaptTutor\\adapttutor\\watcher.py", "source_location": "L38"}, {"caller_nid": "watcher_is_study_title", "callee": "strip", "source_file": "C:\\Users\\Jitendra Pandit\\Downloads\\AdaptTutor\\adapttutor\\watcher.py", "source_location": "L42"}, {"caller_nid": "watcher_extract_page_number", "callee": "strip", "source_file": "C:\\Users\\Jitendra Pandit\\Downloads\\AdaptTutor\\adapttutor\\watcher.py", "source_location": "L54"}, {"caller_nid": "watcher_extract_page_number", "callee": "search", "source_file": "C:\\Users\\Jitendra Pandit\\Downloads\\AdaptTutor\\adapttutor\\watcher.py", "source_location": "L56"}, {"caller_nid": "watcher_extract_page_number", "callee": "int", "source_file": "C:\\Users\\Jitendra Pandit\\Downloads\\AdaptTutor\\adapttutor\\watcher.py", "source_location": "L60"}, {"caller_nid": "watcher_extract_page_number", "callee": "group", "source_file": "C:\\Users\\Jitendra Pandit\\Downloads\\AdaptTutor\\adapttutor\\watcher.py", "source_location": "L60"}, {"caller_nid": "watcher_windowwatcher_init", "callee": "super", "source_file": "C:\\Users\\Jitendra Pandit\\Downloads\\AdaptTutor\\adapttutor\\watcher.py", "source_location": "L83"}, {"caller_nid": "watcher_windowwatcher_init", "callee": "Event", "source_file": "C:\\Users\\Jitendra Pandit\\Downloads\\AdaptTutor\\adapttutor\\watcher.py", "source_location": "L88"}, {"caller_nid": "watcher_windowwatcher_init", "callee": "Lock", "source_file": "C:\\Users\\Jitendra Pandit\\Downloads\\AdaptTutor\\adapttutor\\watcher.py", "source_location": "L89"}, {"caller_nid": "watcher_windowwatcher_stop", "callee": "set", "source_file": "C:\\Users\\Jitendra Pandit\\Downloads\\AdaptTutor\\adapttutor\\watcher.py", "source_location": "L99"}, {"caller_nid": "watcher_windowwatcher_run", "callee": "is_set", "source_file": "C:\\Users\\Jitendra Pandit\\Downloads\\AdaptTutor\\adapttutor\\watcher.py", "source_location": "L110"}, {"caller_nid": "watcher_windowwatcher_run", "callee": "print", "source_file": "C:\\Users\\Jitendra Pandit\\Downloads\\AdaptTutor\\adapttutor\\watcher.py", "source_location": "L112"}, {"caller_nid": "watcher_windowwatcher_run", "callee": "_on_change", "source_file": "C:\\Users\\Jitendra Pandit\\Downloads\\AdaptTutor\\adapttutor\\watcher.py", "source_location": "L126"}, {"caller_nid": "watcher_windowwatcher_run", "callee": "_show_launcher", "source_file": "C:\\Users\\Jitendra Pandit\\Downloads\\AdaptTutor\\adapttutor\\watcher.py", "source_location": "L135"}, {"caller_nid": "watcher_windowwatcher_run", "callee": "_hide_launcher", "source_file": "C:\\Users\\Jitendra Pandit\\Downloads\\AdaptTutor\\adapttutor\\watcher.py", "source_location": "L141"}, {"caller_nid": "watcher_windowwatcher_run", "callee": "wait", "source_file": "C:\\Users\\Jitendra Pandit\\Downloads\\AdaptTutor\\adapttutor\\watcher.py", "source_location": "L149"}]}