{"nodes": [{"id": "c_users_jitendra_pandit_downloads_adapttutor_adapttutor_features_explain_differently_py", "label": "explain_differently.py", "file_type": "code", "source_file": "C:\\Users\\Jitendra Pandit\\Downloads\\AdaptTutor\\adapttutor\\features\\explain_differently.py", "source_location": "L1"}, {"id": "explain_differently_get_windows_work_area", "label": "_get_windows_work_area()", "file_type": "code", "source_file": "C:\\Users\\Jitendra Pandit\\Downloads\\AdaptTutor\\adapttutor\\features\\explain_differently.py", "source_location": "L40"}, {"id": "explain_differently_parse_explain_json", "label": "parse_explain_json()", "file_type": "code", "source_file": "C:\\Users\\Jitendra Pandit\\Downloads\\AdaptTutor\\adapttutor\\features\\explain_differently.py", "source_location": "L61"}, {"id": "explain_differently_explaindifferentlypanel", "label": "ExplainDifferentlyPanel", "file_type": "code", "source_file": "C:\\Users\\Jitendra Pandit\\Downloads\\AdaptTutor\\adapttutor\\features\\explain_differently.py", "source_location": "L91"}, {"id": "explain_differently_explaindifferentlypanel_init", "label": ".__init__()", "file_type": "code", "source_file": "C:\\Users\\Jitendra Pandit\\Downloads\\AdaptTutor\\adapttutor\\features\\explain_differently.py", "source_location": "L97"}, {"id": "explain_differently_explaindifferentlypanel_clear_placeholder", "label": "._clear_placeholder()", "file_type": "code", "source_file": "C:\\Users\\Jitendra Pandit\\Downloads\\AdaptTutor\\adapttutor\\features\\explain_differently.py", "source_location": "L201"}, {"id": "explain_differently_explaindifferentlypanel_restore_placeholder", "label": "._restore_placeholder()", "file_type": "code", "source_file": "C:\\Users\\Jitendra Pandit\\Downloads\\AdaptTutor\\adapttutor\\features\\explain_differently.py", "source_location": "L207"}, {"id": "explain_differently_explaindifferentlypanel_make_card", "label": "._make_card()", "file_type": "code", "source_file": "C:\\Users\\Jitendra Pandit\\Downloads\\AdaptTutor\\adapttutor\\features\\explain_differently.py", "source_location": "L214"}, {"id": "explain_differently_explaindifferentlypanel_set_card_text", "label": "._set_card_text()", "file_type": "code", "source_file": "C:\\Users\\Jitendra Pandit\\Downloads\\AdaptTutor\\adapttutor\\features\\explain_differently.py", "source_location": "L257"}, {"id": "explain_differently_explaindifferentlypanel_set_cards_loading", "label": "._set_cards_loading()", "file_type": "code", "source_file": "C:\\Users\\Jitendra Pandit\\Downloads\\AdaptTutor\\adapttutor\\features\\explain_differently.py", "source_location": "L266"}, {"id": "explain_differently_explaindifferentlypanel_concept_value", "label": "._concept_value()", "file_type": "code", "source_file": "C:\\Users\\Jitendra Pandit\\Downloads\\AdaptTutor\\adapttutor\\features\\explain_differently.py", "source_location": "L270"}, {"id": "explain_differently_explaindifferentlypanel_on_submit", "label": "._on_submit()", "file_type": "code", "source_file": "C:\\Users\\Jitendra Pandit\\Downloads\\AdaptTutor\\adapttutor\\features\\explain_differently.py", "source_location": "L276"}, {"id": "explain_differently_explaindifferentlypanel_reposition_to_launcher", "label": ".reposition_to_launcher()", "file_type": "code", "source_file": "C:\\Users\\Jitendra Pandit\\Downloads\\AdaptTutor\\adapttutor\\features\\explain_differently.py", "source_location": "L318"}, {"id": "explain_differently_explaindifferentlypanel_destroy", "label": ".destroy()", "file_type": "code", "source_file": "C:\\Users\\Jitendra Pandit\\Downloads\\AdaptTutor\\adapttutor\\features\\explain_differently.py", "source_location": "L335"}, {"id": "explain_differently_rationale_62", "label": "Parse model output into simple / analogy / technical strings.", "file_type": "rationale", "source_file": "C:\\Users\\Jitendra Pandit\\Downloads\\AdaptTutor\\adapttutor\\features\\explain_differently.py", "source_location": "L62"}, {"id": "explain_differently_rationale_92", "label": "Concept input, Submit \u2192 three cards (Simple / Analogy / Technical), follow-up fi", "file_type": "rationale", "source_file": "C:\\Users\\Jitendra Pandit\\Downloads\\AdaptTutor\\adapttutor\\features\\explain_differently.py", "source_location": "L92"}], "edges": [{"source": "c_users_jitendra_pandit_downloads_adapttutor_adapttutor_features_explain_differently_py", "target": "ctypes", "relation": "imports", "confidence": "EXTRACTED", "source_file": "C:\\Users\\Jitendra Pandit\\Downloads\\AdaptTutor\\adapttutor\\features\\explain_differently.py", "source_location": "L3", "weight": 1.0}, {"source": "c_users_jitendra_pandit_downloads_adapttutor_adapttutor_features_explain_differently_py", "target": "json", "relation": "imports", "confidence": "EXTRACTED", "source_file": "C:\\Users\\Jitendra Pandit\\Downloads\\AdaptTutor\\adapttutor\\features\\explain_differently.py", "source_location": "L4", "weight": 1.0}, {"source": "c_users_jitendra_pandit_downloads_adapttutor_adapttutor_features_explain_differently_py", "target": "re", "relation": "imports", "confidence": "EXTRACTED", "source_file": "C:\\Users\\Jitendra Pandit\\Downloads\\AdaptTutor\\adapttutor\\features\\explain_differently.py", "source_location": "L5", "weight": 1.0}, {"source": "c_users_jitendra_pandit_downloads_adapttutor_adapttutor_features_explain_differently_py", "target": "ctypes", "relation": "imports_from", "confidence": "EXTRACTED", "source_file": "C:\\Users\\Jitendra Pandit\\Downloads\\AdaptTutor\\adapttutor\\features\\explain_differently.py", "source_location": "L6", "weight": 1.0}, {"source": "c_users_jitendra_pandit_downloads_adapttutor_adapttutor_features_explain_differently_py", "target": "tkinter", "relation": "imports", "confidence": "EXTRACTED", "source_file": "C:\\Users\\Jitendra Pandit\\Downloads\\AdaptTutor\\adapttutor\\features\\explain_differently.py", "source_location": "L7", "weight": 1.0}, {"source": "c_users_jitendra_pandit_downloads_adapttutor_adapttutor_features_explain_differently_py", "target": "tkinter", "relation": "imports_from", "confidence": "EXTRACTED", "source_file": "C:\\Users\\Jitendra Pandit\\Downloads\\AdaptTutor\\adapttutor\\features\\explain_differently.py", "source_location": "L8", "weight": 1.0}, {"source": "c_users_jitendra_pandit_downloads_adapttutor_adapttutor_features_explain_differently_py", "target": "typing", "relation": "imports_from", "confidence": "EXTRACTED", "source_file": "C:\\Users\\Jitendra Pandit\\Downloads\\AdaptTutor\\adapttutor\\features\\explain_differently.py", "source_location": "L9", "weight": 1.0}, {"source": "c_users_jitendra_pandit_downloads_adapttutor_adapttutor_features_explain_differently_py", "target": "c_users_jitendra_pandit_downloads_adapttutor_adapttutor_config_py", "relation": "imports_from", "confidence": "EXTRACTED", "source_file": "C:\\Users\\Jitendra Pandit\\Downloads\\AdaptTutor\\adapttutor\\features\\explain_differently.py", "source_location": "L11", "weight": 1.0}, {"source": "c_users_jitendra_pandit_downloads_adapttutor_adapttutor_features_explain_differently_py", "target": "c_users_jitendra_pandit_downloads_adapttutor_adapttutor_theme_py", "relation": "imports_from", "confidence": "EXTRACTED", "source_file": "C:\\Users\\Jitendra Pandit\\Downloads\\AdaptTutor\\adapttutor\\features\\explain_differently.py", "source_location": "L12", "weight": 1.0}, {"source": "c_users_jitendra_pandit_downloads_adapttutor_adapttutor_features_explain_differently_py", "target": "c_users_jitendra_pandit_downloads_adapttutor_adapttutor_tutor_py", "relation": "imports_from", "confidence": "EXTRACTED", "source_file": "C:\\Users\\Jitendra Pandit\\Downloads\\AdaptTutor\\adapttutor\\features\\explain_differently.py", "source_location": "L13", "weight": 1.0}, {"source": "c_users_jitendra_pandit_downloads_adapttutor_adapttutor_features_explain_differently_py", "target": "explain_differently_get_windows_work_area", "relation": "contains", "confidence": "EXTRACTED", "source_file": "C:\\Users\\Jitendra Pandit\\Downloads\\AdaptTutor\\adapttutor\\features\\explain_differently.py", "source_location": "L40", "weight": 1.0}, {"source": "c_users_jitendra_pandit_downloads_adapttutor_adapttutor_features_explain_differently_py", "target": "explain_differently_parse_explain_json", "relation": "contains", "confidence": "EXTRACTED", "source_file": "C:\\Users\\Jitendra Pandit\\Downloads\\AdaptTutor\\adapttutor\\features\\explain_differently.py", "source_location": "L61", "weight": 1.0}, {"source": "c_users_jitendra_pandit_downloads_adapttutor_adapttutor_features_explain_differently_py", "target": "explain_differently_explaindifferentlypanel", "relation": "contains", "confidence": "EXTRACTED", "source_file": "C:\\Users\\Jitendra Pandit\\Downloads\\AdaptTutor\\adapttutor\\features\\explain_differently.py", "source_location": "L91", "weight": 1.0}, {"source": "explain_differently_explaindifferentlypanel", "target": "explain_differently_explaindifferentlypanel_init", "relation": "method", "confidence": "EXTRACTED", "source_file": "C:\\Users\\Jitendra Pandit\\Downloads\\AdaptTutor\\adapttutor\\features\\explain_differently.py", "source_location": "L97", "weight": 1.0}, {"source": "explain_differently_explaindifferentlypanel", "target": "explain_differently_explaindifferentlypanel_clear_placeholder", "relation": "method", "confidence": "EXTRACTED", "source_file": "C:\\Users\\Jitendra Pandit\\Downloads\\AdaptTutor\\adapttutor\\features\\explain_differently.py", "source_location": "L201", "weight": 1.0}, {"source": "explain_differently_explaindifferentlypanel", "target": "explain_differently_explaindifferentlypanel_restore_placeholder", "relation": "method", "confidence": "EXTRACTED", "source_file": "C:\\Users\\Jitendra Pandit\\Downloads\\AdaptTutor\\adapttutor\\features\\explain_differently.py", "source_location": "L207", "weight": 1.0}, {"source": "explain_differently_explaindifferentlypanel", "target": "explain_differently_explaindifferentlypanel_make_card", "relation": "method", "confidence": "EXTRACTED", "source_file": "C:\\Users\\Jitendra Pandit\\Downloads\\AdaptTutor\\adapttutor\\features\\explain_differently.py", "source_location": "L214", "weight": 1.0}, {"source": "explain_differently_explaindifferentlypanel", "target": "explain_differently_explaindifferentlypanel_set_card_text", "relation": "method", "confidence": "EXTRACTED", "source_file": "C:\\Users\\Jitendra Pandit\\Downloads\\AdaptTutor\\adapttutor\\features\\explain_differently.py", "source_location": "L257", "weight": 1.0}, {"source": "explain_differently_explaindifferentlypanel", "target": "explain_differently_explaindifferentlypanel_set_cards_loading", "relation": "method", "confidence": "EXTRACTED", "source_file": "C:\\Users\\Jitendra Pandit\\Downloads\\AdaptTutor\\adapttutor\\features\\explain_differently.py", "source_location": "L266", "weight": 1.0}, {"source": "explain_differently_explaindifferentlypanel", "target": "explain_differently_explaindifferentlypanel_concept_value", "relation": "method", "confidence": "EXTRACTED", "source_file": "C:\\Users\\Jitendra Pandit\\Downloads\\AdaptTutor\\adapttutor\\features\\explain_differently.py", "source_location": "L270", "weight": 1.0}, {"source": "explain_differently_explaindifferentlypanel", "target": "explain_differently_explaindifferentlypanel_on_submit", "relation": "method", "confidence": "EXTRACTED", "source_file": "C:\\Users\\Jitendra Pandit\\Downloads\\AdaptTutor\\adapttutor\\features\\explain_differently.py", "source_location": "L276", "weight": 1.0}, {"source": "explain_differently_explaindifferentlypanel", "target": "explain_differently_explaindifferentlypanel_reposition_to_launcher", "relation": "method", "confidence": "EXTRACTED", "source_file": "C:\\Users\\Jitendra Pandit\\Downloads\\AdaptTutor\\adapttutor\\features\\explain_differently.py", "source_location": "L318", "weight": 1.0}, {"source": "explain_differently_explaindifferentlypanel", "target": "explain_differently_explaindifferentlypanel_destroy", "relation": "method", "confidence": "EXTRACTED", "source_file": "C:\\Users\\Jitendra Pandit\\Downloads\\AdaptTutor\\adapttutor\\features\\explain_differently.py", "source_location": "L335", "weight": 1.0}, {"source": "explain_differently_explaindifferentlypanel_init", "target": "explain_differently_explaindifferentlypanel_make_card", "relation": "calls", "confidence": "EXTRACTED", "source_file": "C:\\Users\\Jitendra Pandit\\Downloads\\AdaptTutor\\adapttutor\\features\\explain_differently.py", "source_location": "L179", "weight": 1.0}, {"source": "explain_differently_explaindifferentlypanel_init", "target": "explain_differently_explaindifferentlypanel_set_cards_loading", "relation": "calls", "confidence": "EXTRACTED", "source_file": "C:\\Users\\Jitendra Pandit\\Downloads\\AdaptTutor\\adapttutor\\features\\explain_differently.py", "source_location": "L197", "weight": 1.0}, {"source": "explain_differently_explaindifferentlypanel_set_cards_loading", "target": "explain_differently_explaindifferentlypanel_set_card_text", "relation": "calls", "confidence": "EXTRACTED", "source_file": "C:\\Users\\Jitendra Pandit\\Downloads\\AdaptTutor\\adapttutor\\features\\explain_differently.py", "source_location": "L268", "weight": 1.0}, {"source": "explain_differently_explaindifferentlypanel_on_submit", "target": "explain_differently_explaindifferentlypanel_concept_value", "relation": "calls", "confidence": "EXTRACTED", "source_file": "C:\\Users\\Jitendra Pandit\\Downloads\\AdaptTutor\\adapttutor\\features\\explain_differently.py", "source_location": "L277", "weight": 1.0}, {"source": "explain_differently_explaindifferentlypanel_on_submit", "target": "explain_differently_explaindifferentlypanel_set_cards_loading", "relation": "calls", "confidence": "EXTRACTED", "source_file": "C:\\Users\\Jitendra Pandit\\Downloads\\AdaptTutor\\adapttutor\\features\\explain_differently.py", "source_location": "L283", "weight": 1.0}, {"source": "explain_differently_explaindifferentlypanel_reposition_to_launcher", "target": "explain_differently_get_windows_work_area", "relation": "calls", "confidence": "EXTRACTED", "source_file": "C:\\Users\\Jitendra Pandit\\Downloads\\AdaptTutor\\adapttutor\\features\\explain_differently.py", "source_location": "L321", "weight": 1.0}, {"source": "explain_differently_rationale_62", "target": "explain_differently_parse_explain_json", "relation": "rationale_for", "confidence": "EXTRACTED", "source_file": "C:\\Users\\Jitendra Pandit\\Downloads\\AdaptTutor\\adapttutor\\features\\explain_differently.py", "source_location": "L62", "weight": 1.0}, {"source": "explain_differently_rationale_92", "target": "explain_differently_explaindifferentlypanel", "relation": "rationale_for", "confidence": "EXTRACTED", "source_file": "C:\\Users\\Jitendra Pandit\\Downloads\\AdaptTutor\\adapttutor\\features\\explain_differently.py", "source_location": "L92", "weight": 1.0}], "raw_calls": [{"caller_nid": "explain_differently_get_windows_work_area", "callee": "RECT", "source_file": "C:\\Users\\Jitendra Pandit\\Downloads\\AdaptTutor\\adapttutor\\features\\explain_differently.py", "source_location": "L52"}, {"caller_nid": "explain_differently_get_windows_work_area", "callee": "SystemParametersInfoW", "source_file": "C:\\Users\\Jitendra Pandit\\Downloads\\AdaptTutor\\adapttutor\\features\\explain_differently.py", "source_location": "L53"}, {"caller_nid": "explain_differently_get_windows_work_area", "callee": "byref", "source_file": "C:\\Users\\Jitendra Pandit\\Downloads\\AdaptTutor\\adapttutor\\features\\explain_differently.py", "source_location": "L53"}, {"caller_nid": "explain_differently_get_windows_work_area", "callee": "int", "source_file": "C:\\Users\\Jitendra Pandit\\Downloads\\AdaptTutor\\adapttutor\\features\\explain_differently.py", "source_location": "L56"}, {"caller_nid": "explain_differently_get_windows_work_area", "callee": "int", "source_file": "C:\\Users\\Jitendra Pandit\\Downloads\\AdaptTutor\\adapttutor\\features\\explain_differently.py", "source_location": "L56"}, {"caller_nid": "explain_differently_get_windows_work_area", "callee": "int", "source_file": "C:\\Users\\Jitendra Pandit\\Downloads\\AdaptTutor\\adapttutor\\features\\explain_differently.py", "source_location": "L56"}, {"caller_nid": "explain_differently_get_windows_work_area", "callee": "int", "source_file": "C:\\Users\\Jitendra Pandit\\Downloads\\AdaptTutor\\adapttutor\\features\\explain_differently.py", "source_location": "L56"}, {"caller_nid": "explain_differently_parse_explain_json", "callee": "strip", "source_file": "C:\\Users\\Jitendra Pandit\\Downloads\\AdaptTutor\\adapttutor\\features\\explain_differently.py", "source_location": "L63"}, {"caller_nid": "explain_differently_parse_explain_json", "callee": "ValueError", "source_file": "C:\\Users\\Jitendra Pandit\\Downloads\\AdaptTutor\\adapttutor\\features\\explain_differently.py", "source_location": "L65"}, {"caller_nid": "explain_differently_parse_explain_json", "callee": "startswith", "source_file": "C:\\Users\\Jitendra Pandit\\Downloads\\AdaptTutor\\adapttutor\\features\\explain_differently.py", "source_location": "L67"}, {"caller_nid": "explain_differently_parse_explain_json", "callee": "sub", "source_file": "C:\\Users\\Jitendra Pandit\\Downloads\\AdaptTutor\\adapttutor\\features\\explain_differently.py", "source_location": "L68"}, {"caller_nid": "explain_differently_parse_explain_json", "callee": "strip", "source_file": "C:\\Users\\Jitendra Pandit\\Downloads\\AdaptTutor\\adapttutor\\features\\explain_differently.py", "source_location": "L69"}, {"caller_nid": "explain_differently_parse_explain_json", "callee": "sub", "source_file": "C:\\Users\\Jitendra Pandit\\Downloads\\AdaptTutor\\adapttutor\\features\\explain_differently.py", "source_location": "L69"}, {"caller_nid": "explain_differently_parse_explain_json", "callee": "loads", "source_file": "C:\\Users\\Jitendra Pandit\\Downloads\\AdaptTutor\\adapttutor\\features\\explain_differently.py", "source_location": "L71"}, {"caller_nid": "explain_differently_parse_explain_json", "callee": "isinstance", "source_file": "C:\\Users\\Jitendra Pandit\\Downloads\\AdaptTutor\\adapttutor\\features\\explain_differently.py", "source_location": "L72"}, {"caller_nid": "explain_differently_parse_explain_json", "callee": "ValueError", "source_file": "C:\\Users\\Jitendra Pandit\\Downloads\\AdaptTutor\\adapttutor\\features\\explain_differently.py", "source_location": "L73"}, {"caller_nid": "explain_differently_parse_explain_json", "callee": "pick", "source_file": "C:\\Users\\Jitendra Pandit\\Downloads\\AdaptTutor\\adapttutor\\features\\explain_differently.py", "source_location": "L83"}, {"caller_nid": "explain_differently_parse_explain_json", "callee": "pick", "source_file": "C:\\Users\\Jitendra Pandit\\Downloads\\AdaptTutor\\adapttutor\\features\\explain_differently.py", "source_location": "L84"}, {"caller_nid": "explain_differently_parse_explain_json", "callee": "pick", "source_file": "C:\\Users\\Jitendra Pandit\\Downloads\\AdaptTutor\\adapttutor\\features\\explain_differently.py", "source_location": "L85"}, {"caller_nid": "explain_differently_parse_explain_json", "callee": "ValueError", "source_file": "C:\\Users\\Jitendra Pandit\\Downloads\\AdaptTutor\\adapttutor\\features\\explain_differently.py", "source_location": "L87"}, {"caller_nid": "explain_differently_explaindifferentlypanel_init", "callee": "Toplevel", "source_file": "C:\\Users\\Jitendra Pandit\\Downloads\\AdaptTutor\\adapttutor\\features\\explain_differently.py", "source_location": "L110"}, {"caller_nid": "explain_differently_explaindifferentlypanel_init", "callee": "overrideredirect", "source_file": "C:\\Users\\Jitendra Pandit\\Downloads\\AdaptTutor\\adapttutor\\features\\explain_differently.py", "source_location": "L111"}, {"caller_nid": "explain_differently_explaindifferentlypanel_init", "callee": "apply_topmost", "source_file": "C:\\Users\\Jitendra Pandit\\Downloads\\AdaptTutor\\adapttutor\\features\\explain_differently.py", "source_location": "L112"}, {"caller_nid": "explain_differently_explaindifferentlypanel_init", "callee": "configure", "source_file": "C:\\Users\\Jitendra Pandit\\Downloads\\AdaptTutor\\adapttutor\\features\\explain_differently.py", "source_location": "L113"}, {"caller_nid": "explain_differently_explaindifferentlypanel_init", "callee": "Frame", "source_file": "C:\\Users\\Jitendra Pandit\\Downloads\\AdaptTutor\\adapttutor\\features\\explain_differently.py", "source_location": "L115"}, {"caller_nid": "explain_differently_explaindifferentlypanel_init", "callee": "pack", "source_file": "C:\\Users\\Jitendra Pandit\\Downloads\\AdaptTutor\\adapttutor\\features\\explain_differently.py", "source_location": "L116"}, {"caller_nid": "explain_differently_explaindifferentlypanel_init", "callee": "pack", "source_file": "C:\\Users\\Jitendra Pandit\\Downloads\\AdaptTutor\\adapttutor\\features\\explain_differently.py", "source_location": "L118"}, {"caller_nid": "explain_differently_explaindifferentlypanel_init", "callee": "Label", "source_file": "C:\\Users\\Jitendra Pandit\\Downloads\\AdaptTutor\\adapttutor\\features\\explain_differently.py", "source_location": "L118"}, {"caller_nid": "explain_differently_explaindifferentlypanel_init", "callee": "Label", "source_file": "C:\\Users\\Jitendra Pandit\\Downloads\\AdaptTutor\\adapttutor\\features\\explain_differently.py", "source_location": "L121"}, {"caller_nid": "explain_differently_explaindifferentlypanel_init", "callee": "pack", "source_file": "C:\\Users\\Jitendra Pandit\\Downloads\\AdaptTutor\\adapttutor\\features\\explain_differently.py", "source_location": "L122"}, {"caller_nid": "explain_differently_explaindifferentlypanel_init", "callee": "bind", "source_file": "C:\\Users\\Jitendra Pandit\\Downloads\\AdaptTutor\\adapttutor\\features\\explain_differently.py", "source_location": "L123"}, {"caller_nid": "explain_differently_explaindifferentlypanel_init", "callee": "_on_close", "source_file": "C:\\Users\\Jitendra Pandit\\Downloads\\AdaptTutor\\adapttutor\\features\\explain_differently.py", "source_location": "L123"}, {"caller_nid": "explain_differently_explaindifferentlypanel_init", "callee": "Frame", "source_file": "C:\\Users\\Jitendra Pandit\\Downloads\\AdaptTutor\\adapttutor\\features\\explain_differently.py", "source_location": "L125"}, {"caller_nid": "explain_differently_explaindifferentlypanel_init", "callee": "pack", "source_file": "C:\\Users\\Jitendra Pandit\\Downloads\\AdaptTutor\\adapttutor\\features\\explain_differently.py", "source_location": "L126"}, {"caller_nid": "explain_differently_explaindifferentlypanel_init", "callee": "Scrollbar", "source_file": "C:\\Users\\Jitendra Pandit\\Downloads\\AdaptTutor\\adapttutor\\features\\explain_differently.py", "source_location": "L128"}, {"caller_nid": "explain_differently_explaindifferentlypanel_init", "callee": "pack", "source_file": "C:\\Users\\Jitendra Pandit\\Downloads\\AdaptTutor\\adapttutor\\features\\explain_differently.py", "source_location": "L129"}, {"caller_nid": "explain_differently_explaindifferentlypanel_init", "callee": "Canvas", "source_file": "C:\\Users\\Jitendra Pandit\\Downloads\\AdaptTutor\\adapttutor\\features\\explain_differently.py", "source_location": "L130"}, {"caller_nid": "explain_differently_explaindifferentlypanel_init", "callee": "pack", "source_file": "C:\\Users\\Jitendra Pandit\\Downloads\\AdaptTutor\\adapttutor\\features\\explain_differently.py", "source_location": "L131"}, {"caller_nid": "explain_differently_explaindifferentlypanel_init", "callee": "config", "source_file": "C:\\Users\\Jitendra Pandit\\Downloads\\AdaptTutor\\adapttutor\\features\\explain_differently.py", "source_location": "L132"}, {"caller_nid": "explain_differently_explaindifferentlypanel_init", "callee": "Frame", "source_file": "C:\\Users\\Jitendra Pandit\\Downloads\\AdaptTutor\\adapttutor\\features\\explain_differently.py", "source_location": "L134"}, {"caller_nid": "explain_differently_explaindifferentlypanel_init", "callee": "create_window", "source_file": "C:\\Users\\Jitendra Pandit\\Downloads\\AdaptTutor\\adapttutor\\features\\explain_differently.py", "source_location": "L135"}, {"caller_nid": "explain_differently_explaindifferentlypanel_init", "callee": "bind", "source_file": "C:\\Users\\Jitendra Pandit\\Downloads\\AdaptTutor\\adapttutor\\features\\explain_differently.py", "source_location": "L141"}, {"caller_nid": "explain_differently_explaindifferentlypanel_init", "callee": "bind", "source_file": "C:\\Users\\Jitendra Pandit\\Downloads\\AdaptTutor\\adapttutor\\features\\explain_differently.py", "source_location": "L142"}, {"caller_nid": "explain_differently_explaindifferentlypanel_init", "callee": "pack", "source_file": "C:\\Users\\Jitendra Pandit\\Downloads\\AdaptTutor\\adapttutor\\features\\explain_differently.py", "source_location": "L144"}, {"caller_nid": "explain_differently_explaindifferentlypanel_init", "callee": "Label", "source_file": "C:\\Users\\Jitendra Pandit\\Downloads\\AdaptTutor\\adapttutor\\features\\explain_differently.py", "source_location": "L144"}, {"caller_nid": "explain_differently_explaindifferentlypanel_init", "callee": "Text", "source_file": "C:\\Users\\Jitendra Pandit\\Downloads\\AdaptTutor\\adapttutor\\features\\explain_differently.py", "source_location": "L145"}, {"caller_nid": "explain_differently_explaindifferentlypanel_init", "callee": "pack", "source_file": "C:\\Users\\Jitendra Pandit\\Downloads\\AdaptTutor\\adapttutor\\features\\explain_differently.py", "source_location": "L153"}, {"caller_nid": "explain_differently_explaindifferentlypanel_init", "callee": "style_text_editable", "source_file": "C:\\Users\\Jitendra Pandit\\Downloads\\AdaptTutor\\adapttutor\\features\\explain_differently.py", "source_location": "L154"}, {"caller_nid": "explain_differently_explaindifferentlypanel_init", "callee": "insert", "source_file": "C:\\Users\\Jitendra Pandit\\Downloads\\AdaptTutor\\adapttutor\\features\\explain_differently.py", "source_location": "L156"}, {"caller_nid": "explain_differently_explaindifferentlypanel_init", "callee": "configure", "source_file": "C:\\Users\\Jitendra Pandit\\Downloads\\AdaptTutor\\adapttutor\\features\\explain_differently.py", "source_location": "L157"}, {"caller_nid": "explain_differently_explaindifferentlypanel_init", "callee": "bind", "source_file": "C:\\Users\\Jitendra Pandit\\Downloads\\AdaptTutor\\adapttutor\\features\\explain_differently.py", "source_location": "L158"}, {"caller_nid": "explain_differently_explaindifferentlypanel_init", "callee": "bind", "source_file": "C:\\Users\\Jitendra Pandit\\Downloads\\AdaptTutor\\adapttutor\\features\\explain_differently.py", "source_location": "L159"}, {"caller_nid": "explain_differently_explaindifferentlypanel_init", "callee": "Frame", "source_file": "C:\\Users\\Jitendra Pandit\\Downloads\\AdaptTutor\\adapttutor\\features\\explain_differently.py", "source_location": "L162"}, {"caller_nid": "explain_differently_explaindifferentlypanel_init", "callee": "pack", "source_file": "C:\\Users\\Jitendra Pandit\\Downloads\\AdaptTutor\\adapttutor\\features\\explain_differently.py", "source_location": "L163"}, {"caller_nid": "explain_differently_explaindifferentlypanel_init", "callee": "Button", "source_file": "C:\\Users\\Jitendra Pandit\\Downloads\\AdaptTutor\\adapttutor\\features\\explain_differently.py", "source_location": "L164"}, {"caller_nid": "explain_differently_explaindifferentlypanel_init", "callee": "pack", "source_file": "C:\\Users\\Jitendra Pandit\\Downloads\\AdaptTutor\\adapttutor\\features\\explain_differently.py", "source_location": "L165"}, {"caller_nid": "explain_differently_explaindifferentlypanel_init", "callee": "style_button", "source_file": "C:\\Users\\Jitendra Pandit\\Downloads\\AdaptTutor\\adapttutor\\features\\explain_differently.py", "source_location": "L166"}, {"caller_nid": "explain_differently_explaindifferentlypanel_init", "callee": "Label", "source_file": "C:\\Users\\Jitendra Pandit\\Downloads\\AdaptTutor\\adapttutor\\features\\explain_differently.py", "source_location": "L167"}, {"caller_nid": "explain_differently_explaindifferentlypanel_init", "callee": "pack", "source_file": "C:\\Users\\Jitendra Pandit\\Downloads\\AdaptTutor\\adapttutor\\features\\explain_differently.py", "source_location": "L174"}, {"caller_nid": "explain_differently_explaindifferentlypanel_init", "callee": "Frame", "source_file": "C:\\Users\\Jitendra Pandit\\Downloads\\AdaptTutor\\adapttutor\\features\\explain_differently.py", "source_location": "L176"}, {"caller_nid": "explain_differently_explaindifferentlypanel_init", "callee": "pack", "source_file": "C:\\Users\\Jitendra Pandit\\Downloads\\AdaptTutor\\adapttutor\\features\\explain_differently.py", "source_location": "L177"}, {"caller_nid": "explain_differently_explaindifferentlypanel_init", "callee": "pack", "source_file": "C:\\Users\\Jitendra Pandit\\Downloads\\AdaptTutor\\adapttutor\\features\\explain_differently.py", "source_location": "L183"}, {"caller_nid": "explain_differently_explaindifferentlypanel_init", "callee": "Label", "source_file": "C:\\Users\\Jitendra Pandit\\Downloads\\AdaptTutor\\adapttutor\\features\\explain_differently.py", "source_location": "L183"}, {"caller_nid": "explain_differently_explaindifferentlypanel_init", "callee": "Text", "source_file": "C:\\Users\\Jitendra Pandit\\Downloads\\AdaptTutor\\adapttutor\\features\\explain_differently.py", "source_location": "L186"}, {"caller_nid": "explain_differently_explaindifferentlypanel_init", "callee": "pack", "source_file": "C:\\Users\\Jitendra Pandit\\Downloads\\AdaptTutor\\adapttutor\\features\\explain_differently.py", "source_location": "L194"}, {"caller_nid": "explain_differently_explaindifferentlypanel_init", "callee": "style_text_editable", "source_file": "C:\\Users\\Jitendra Pandit\\Downloads\\AdaptTutor\\adapttutor\\features\\explain_differently.py", "source_location": "L195"}, {"caller_nid": "explain_differently_explaindifferentlypanel_init", "callee": "geometry", "source_file": "C:\\Users\\Jitendra Pandit\\Downloads\\AdaptTutor\\adapttutor\\features\\explain_differently.py", "source_location": "L199"}, {"caller_nid": "explain_differently_explaindifferentlypanel_clear_placeholder", "callee": "strip", "source_file": "C:\\Users\\Jitendra Pandit\\Downloads\\AdaptTutor\\adapttutor\\features\\explain_differently.py", "source_location": "L202"}, {"caller_nid": "explain_differently_explaindifferentlypanel_clear_placeholder", "callee": "get", "source_file": "C:\\Users\\Jitendra Pandit\\Downloads\\AdaptTutor\\adapttutor\\features\\explain_differently.py", "source_location": "L202"}, {"caller_nid": "explain_differently_explaindifferentlypanel_clear_placeholder", "callee": "delete", "source_file": "C:\\Users\\Jitendra Pandit\\Downloads\\AdaptTutor\\adapttutor\\features\\explain_differently.py", "source_location": "L203"}, {"caller_nid": "explain_differently_explaindifferentlypanel_clear_placeholder", "callee": "configure", "source_file": "C:\\Users\\Jitendra Pandit\\Downloads\\AdaptTutor\\adapttutor\\features\\explain_differently.py", "source_location": "L204"}, {"caller_nid": "explain_differently_explaindifferentlypanel_restore_placeholder", "callee": "strip", "source_file": "C:\\Users\\Jitendra Pandit\\Downloads\\AdaptTutor\\adapttutor\\features\\explain_differently.py", "source_location": "L208"}, {"caller_nid": "explain_differently_explaindifferentlypanel_restore_placeholder", "callee": "get", "source_file": "C:\\Users\\Jitendra Pandit\\Downloads\\AdaptTutor\\adapttutor\\features\\explain_differently.py", "source_location": "L208"}, {"caller_nid": "explain_differently_explaindifferentlypanel_restore_placeholder", "callee": "delete", "source_file": "C:\\Users\\Jitendra Pandit\\Downloads\\AdaptTutor\\adapttutor\\features\\explain_differently.py", "source_location": "L210"}, {"caller_nid": "explain_differently_explaindifferentlypanel_restore_placeholder", "callee": "insert", "source_file": "C:\\Users\\Jitendra Pandit\\Downloads\\AdaptTutor\\adapttutor\\features\\explain_differently.py", "source_location": "L211"}, {"caller_nid": "explain_differently_explaindifferentlypanel_restore_placeholder", "callee": "configure", "source_file": "C:\\Users\\Jitendra Pandit\\Downloads\\AdaptTutor\\adapttutor\\features\\explain_differently.py", "source_location": "L212"}, {"caller_nid": "explain_differently_explaindifferentlypanel_make_card", "callee": "Frame", "source_file": "C:\\Users\\Jitendra Pandit\\Downloads\\AdaptTutor\\adapttutor\\features\\explain_differently.py", "source_location": "L216"}, {"caller_nid": "explain_differently_explaindifferentlypanel_make_card", "callee": "pack", "source_file": "C:\\Users\\Jitendra Pandit\\Downloads\\AdaptTutor\\adapttutor\\features\\explain_differently.py", "source_location": "L217"}, {"caller_nid": "explain_differently_explaindifferentlypanel_make_card", "callee": "Frame", "source_file": "C:\\Users\\Jitendra Pandit\\Downloads\\AdaptTutor\\adapttutor\\features\\explain_differently.py", "source_location": "L219"}, {"caller_nid": "explain_differently_explaindifferentlypanel_make_card", "callee": "pack", "source_file": "C:\\Users\\Jitendra Pandit\\Downloads\\AdaptTutor\\adapttutor\\features\\explain_differently.py", "source_location": "L220"}, {"caller_nid": "explain_differently_explaindifferentlypanel_make_card", "callee": "Frame", "source_file": "C:\\Users\\Jitendra Pandit\\Downloads\\AdaptTutor\\adapttutor\\features\\explain_differently.py", "source_location": "L222"}, {"caller_nid": "explain_differently_explaindifferentlypanel_make_card", "callee": "pack", "source_file": "C:\\Users\\Jitendra Pandit\\Downloads\\AdaptTutor\\adapttutor\\features\\explain_differently.py", "source_location": "L223"}, {"caller_nid": "explain_differently_explaindifferentlypanel_make_card", "callee": "Label", "source_file": "C:\\Users\\Jitendra Pandit\\Downloads\\AdaptTutor\\adapttutor\\features\\explain_differently.py", "source_location": "L225"}, {"caller_nid": "explain_differently_explaindifferentlypanel_make_card", "callee": "pack", "source_file": "C:\\Users\\Jitendra Pandit\\Downloads\\AdaptTutor\\adapttutor\\features\\explain_differently.py", "source_location": "L226"}, {"caller_nid": "explain_differently_explaindifferentlypanel_make_card", "callee": "Text", "source_file": "C:\\Users\\Jitendra Pandit\\Downloads\\AdaptTutor\\adapttutor\\features\\explain_differently.py", "source_location": "L228"}, {"caller_nid": "explain_differently_explaindifferentlypanel_make_card", "callee": "pack", "source_file": "C:\\Users\\Jitendra Pandit\\Downloads\\AdaptTutor\\adapttutor\\features\\explain_differently.py", "source_location": "L240"}, {"caller_nid": "explain_differently_explaindifferentlypanel_make_card", "callee": "style_text_readonly", "source_file": "C:\\Users\\Jitendra Pandit\\Downloads\\AdaptTutor\\adapttutor\\features\\explain_differently.py", "source_location": "L241"}, {"caller_nid": "explain_differently_explaindifferentlypanel_make_card", "callee": "bind", "source_file": "C:\\Users\\Jitendra Pandit\\Downloads\\AdaptTutor\\adapttutor\\features\\explain_differently.py", "source_location": "L249"}, {"caller_nid": "explain_differently_explaindifferentlypanel_make_card", "callee": "bind", "source_file": "C:\\Users\\Jitendra Pandit\\Downloads\\AdaptTutor\\adapttutor\\features\\explain_differently.py", "source_location": "L250"}, {"caller_nid": "explain_differently_explaindifferentlypanel_make_card", "callee": "bind", "source_file": "C:\\Users\\Jitendra Pandit\\Downloads\\AdaptTutor\\adapttutor\\features\\explain_differently.py", "source_location": "L251"}, {"caller_nid": "explain_differently_explaindifferentlypanel_make_card", "callee": "bind", "source_file": "C:\\Users\\Jitendra Pandit\\Downloads\\AdaptTutor\\adapttutor\\features\\explain_differently.py", "source_location": "L252"}, {"caller_nid": "explain_differently_explaindifferentlypanel_make_card", "callee": "bind", "source_file": "C:\\Users\\Jitendra Pandit\\Downloads\\AdaptTutor\\adapttutor\\features\\explain_differently.py", "source_location": "L253"}, {"caller_nid": "explain_differently_explaindifferentlypanel_set_card_text", "callee": "isinstance", "source_file": "C:\\Users\\Jitendra Pandit\\Downloads\\AdaptTutor\\adapttutor\\features\\explain_differently.py", "source_location": "L259"}, {"caller_nid": "explain_differently_explaindifferentlypanel_set_card_text", "callee": "configure", "source_file": "C:\\Users\\Jitendra Pandit\\Downloads\\AdaptTutor\\adapttutor\\features\\explain_differently.py", "source_location": "L261"}, {"caller_nid": "explain_differently_explaindifferentlypanel_set_card_text", "callee": "delete", "source_file": "C:\\Users\\Jitendra Pandit\\Downloads\\AdaptTutor\\adapttutor\\features\\explain_differently.py", "source_location": "L262"}, {"caller_nid": "explain_differently_explaindifferentlypanel_set_card_text", "callee": "insert", "source_file": "C:\\Users\\Jitendra Pandit\\Downloads\\AdaptTutor\\adapttutor\\features\\explain_differently.py", "source_location": "L263"}, {"caller_nid": "explain_differently_explaindifferentlypanel_set_card_text", "callee": "configure", "source_file": "C:\\Users\\Jitendra Pandit\\Downloads\\AdaptTutor\\adapttutor\\features\\explain_differently.py", "source_location": "L264"}, {"caller_nid": "explain_differently_explaindifferentlypanel_concept_value", "callee": "strip", "source_file": "C:\\Users\\Jitendra Pandit\\Downloads\\AdaptTutor\\adapttutor\\features\\explain_differently.py", "source_location": "L271"}, {"caller_nid": "explain_differently_explaindifferentlypanel_concept_value", "callee": "get", "source_file": "C:\\Users\\Jitendra Pandit\\Downloads\\AdaptTutor\\adapttutor\\features\\explain_differently.py", "source_location": "L271"}, {"caller_nid": "explain_differently_explaindifferentlypanel_on_submit", "callee": "showwarning", "source_file": "C:\\Users\\Jitendra Pandit\\Downloads\\AdaptTutor\\adapttutor\\features\\explain_differently.py", "source_location": "L279"}, {"caller_nid": "explain_differently_explaindifferentlypanel_on_submit", "callee": "configure", "source_file": "C:\\Users\\Jitendra Pandit\\Downloads\\AdaptTutor\\adapttutor\\features\\explain_differently.py", "source_location": "L282"}, {"caller_nid": "explain_differently_explaindifferentlypanel_on_submit", "callee": "configure", "source_file": "C:\\Users\\Jitendra Pandit\\Downloads\\AdaptTutor\\adapttutor\\features\\explain_differently.py", "source_location": "L284"}, {"caller_nid": "explain_differently_explaindifferentlypanel_on_submit", "callee": "format", "source_file": "C:\\Users\\Jitendra Pandit\\Downloads\\AdaptTutor\\adapttutor\\features\\explain_differently.py", "source_location": "L286"}, {"caller_nid": "explain_differently_explaindifferentlypanel_on_submit", "callee": "ask", "source_file": "C:\\Users\\Jitendra Pandit\\Downloads\\AdaptTutor\\adapttutor\\features\\explain_differently.py", "source_location": "L309"}, {"caller_nid": "explain_differently_explaindifferentlypanel_reposition_to_launcher", "callee": "update_idletasks", "source_file": "C:\\Users\\Jitendra Pandit\\Downloads\\AdaptTutor\\adapttutor\\features\\explain_differently.py", "source_location": "L319"}, {"caller_nid": "explain_differently_explaindifferentlypanel_reposition_to_launcher", "callee": "update_idletasks", "source_file": "C:\\Users\\Jitendra Pandit\\Downloads\\AdaptTutor\\adapttutor\\features\\explain_differently.py", "source_location": "L320"}, {"caller_nid": "explain_differently_explaindifferentlypanel_reposition_to_launcher", "callee": "winfo_screenwidth", "source_file": "C:\\Users\\Jitendra Pandit\\Downloads\\AdaptTutor\\adapttutor\\features\\explain_differently.py", "source_location": "L325"}, {"caller_nid": "explain_differently_explaindifferentlypanel_reposition_to_launcher", "callee": "winfo_screenheight", "source_file": "C:\\Users\\Jitendra Pandit\\Downloads\\AdaptTutor\\adapttutor\\features\\explain_differently.py", "source_location": "L326"}, {"caller_nid": "explain_differently_explaindifferentlypanel_reposition_to_launcher", "callee": "geometry", "source_file": "C:\\Users\\Jitendra Pandit\\Downloads\\AdaptTutor\\adapttutor\\features\\explain_differently.py", "source_location": "L333"}]}